sentralify/__init__.py
sentralify/generators.py
sentralify/scrapers.py
sentralify-1.2.14.dist-info/licenses/LICENSE
sentralify-1.2.14.dist-info/METADATA
sentralify-1.2.14.dist-info/WHEEL
sentralify-1.2.14.dist-info/top_level.txt
sentralify-1.2.14.dist-info/RECORD
