Metadata-Version: 2.4
Name: sentralify
Version: 1.2.14
Summary: Scrape Sentral data and use it!
Author-email: mario872 <jamesaglynn10@gmail.com>
License: GNU GENERAL PUBLIC LICENSE
Project-URL: Homepage, https://github.com/mario872/sentralify
Keywords: sentral,sentralify,scrape,data,school,timetable,time table
Classifier: License :: OSI Approved :: MIT License
Classifier: Programming Language :: Python
Classifier: Programming Language :: Python :: 3
Requires-Python: >=3.10
License-File: LICENSE
Requires-Dist: playwright>=1.41.2
Requires-Dist: beautifulsoup4>=4.12.3
Requires-Dist: lxml>=5.1.0
Requires-Dist: markdownify>=0.11.6
Requires-Dist: python-dateutil>=2.8.2
Dynamic: license-file
